refinerycalc/__init__.py
refinerycalc/api_client.py
refinerycalc/configuration.py
refinerycalc/rest.py
refinerycalc/api/__init__.py
refinerycalc/api/crudes_api.py
refinerycalc/api/end_points_api.py
refinerycalc/api/product_prices_api.py
refinerycalc/api/rate_api.py
refinerycalc/api/refineries_api.py
refinerycalc/api/regions_api.py
refinerycalc/api/simulations_api.py
refinerycalc/api/weather_forecast_api.py
refinerycalc/models/__init__.py
refinerycalc/models/add_refineries_to_simulation_request.py
refinerycalc/models/advanced_option_request.py
refinerycalc/models/advanced_option_type.py
refinerycalc/models/advanced_options_batch_refinery.py
refinerycalc/models/advanced_options_batch_request.py
refinerycalc/models/api_response.py
refinerycalc/models/calculator_crude_price_mode_output_model.py
refinerycalc/models/calculator_model.py
refinerycalc/models/calculator_refinery_crude_reference.py
refinerycalc/models/calculator_refinery_model.py
refinerycalc/models/calculator_refinery_output_model.py
refinerycalc/models/change_end_point_mode_request.py
refinerycalc/models/change_end_point_request.py
refinerycalc/models/create_simulation_request.py
refinerycalc/models/create_simulation_response.py
refinerycalc/models/crude_allocation.py
refinerycalc/models/crude_allocation_value.py
refinerycalc/models/crude_evaluation_mode.py
refinerycalc/models/crude_item.py
refinerycalc/models/crude_mode.py
refinerycalc/models/crude_model.py
refinerycalc/models/crude_price.py
refinerycalc/models/crude_price_mode_crude.py
refinerycalc/models/crude_type.py
refinerycalc/models/data_source.py
refinerycalc/models/end_point_mode.py
refinerycalc/models/end_point_model.py
refinerycalc/models/end_point_response.py
refinerycalc/models/filter_operator.py
refinerycalc/models/get_calculator_refinery_crudes_response.py
refinerycalc/models/get_refineries_for_simulation_response.py
refinerycalc/models/graph.py
refinerycalc/models/graph_model.py
refinerycalc/models/health_state.py
refinerycalc_api-1.0.0.dist-info/METADATA
refinerycalc_api-1.0.0.dist-info/WHEEL
refinerycalc_api-1.0.0.dist-info/top_level.txt
refinerycalc_api-1.0.0.dist-info/RECORD
